qgrid/__init__.py
qgrid/_version.py
qgrid/grid.py
qgrid/static/07260b91004837f64dbfa8cbe0bac27e.png
qgrid/static/097df1053ff3246e2f1af9d5a858ac6c.gif
qgrid/static/1684d197ca78f5eca238.png
qgrid/static/177e96f6b132ebf8fe08.gif
qgrid/static/1d2a1cd0c8e67840e6c1.png
qgrid/static/255ce53c58b905a5f2c3.gif
qgrid/static/5b6d8d7df86d8901bb2a.png
qgrid/static/63f6e1e148d7ef23e4dc.gif
qgrid/static/720ec1bdffac972ae44e.gif
qgrid/static/72d75941846d924d988746d10f4eb5f8.png
qgrid/static/7e2ccbc3b7b736251403b238014dcacc.gif
qgrid/static/80144c4a6481ea5f9cf8.png
qgrid/static/81e9e22e43956977f337.png
qgrid/static/86586a919bd10f4cedba392f64336a54.gif
qgrid/static/8a099d784251854735669301a43b6129.png
qgrid/static/8fcbe60e4efd8e2d1742bba8486994e1.gif
qgrid/static/93d7c60382cc62b79593d9b0c5b4b75c.png
qgrid/static/9a52a923ceb5983fa0943c1e24d6d35b.gif
qgrid/static/9e846664428941e32a6117e58ee24def.png
qgrid/static/a0ba920be46b9e2ea47f.png
qgrid/static/a2b8bfe53991521d8b1d.gif
qgrid/static/d5ce50f40bd2a5707619.gif
qgrid/static/da1e9bc574edaacb992b162ff8cb3b27.png
qgrid/static/e38f33bbf55d6e20d21c4a10b9912668.gif
qgrid/static/extension.js
qgrid/static/index.js
qgrid/static/index.js.LICENSE.txt
qgrid/static/index.js.map
qgridtrusted-0.0.14.data/data/etc/jupyter/nbconfig/notebook.d/qgrid.json
qgridtrusted-0.0.14.data/data/share/jupyter/nbextensions/qgrid/07260b91004837f64dbfa8cbe0bac27e.png
qgridtrusted-0.0.14.data/data/share/jupyter/nbextensions/qgrid/097df1053ff3246e2f1af9d5a858ac6c.gif
qgridtrusted-0.0.14.data/data/share/jupyter/nbextensions/qgrid/1684d197ca78f5eca238.png
qgridtrusted-0.0.14.data/data/share/jupyter/nbextensions/qgrid/177e96f6b132ebf8fe08.gif
qgridtrusted-0.0.14.data/data/share/jupyter/nbextensions/qgrid/1d2a1cd0c8e67840e6c1.png
qgridtrusted-0.0.14.data/data/share/jupyter/nbextensions/qgrid/255ce53c58b905a5f2c3.gif
qgridtrusted-0.0.14.data/data/share/jupyter/nbextensions/qgrid/5b6d8d7df86d8901bb2a.png
qgridtrusted-0.0.14.dist-info/LICENSE
qgridtrusted-0.0.14.dist-info/METADATA
qgridtrusted-0.0.14.dist-info/WHEEL
qgridtrusted-0.0.14.dist-info/top_level.txt
qgridtrusted-0.0.14.dist-info/RECORD
