Metadata-Version: 2.1
Name: qgridtrusted
Version: 0.0.14
Summary: A fork of qgrid using trusted publishing.
Author-email: Keith Maxwell <keith.maxwell@gmail.com>, "Quantopian Inc." <opensource@quantopian.com>
License: 
Project-URL: Homepage, https://github.com/maxwell-k/qgridtrusted/
Keywords: ipython,jupyter,widgets
Classifier: Development Status :: 4 - Beta
Classifier: Framework :: IPython
Classifier: Intended Audience :: Developers
Classifier: Intended Audience :: Science/Research
Classifier: Topic :: Office/Business :: Financial
Classifier: Topic :: Scientific/Engineering :: Information Analysis
Classifier: Topic :: Multimedia :: Graphics
Classifier: Programming Language :: Python :: 3
Classifier: Programming Language :: Python :: 3.11
Classifier: Programming Language :: Python :: 3.12
License-File: LICENSE
Requires-Dist: nbclassic
Requires-Dist: pandas
Requires-Dist: ipywidgets
Provides-Extra: test
Requires-Dist: pytest ; extra == 'test'
Requires-Dist: flake8 ; extra == 'test'
Requires-Dist: pandas-stubs ; extra == 'test'
Requires-Dist: usort ; extra == 'test'
